taglogger/__init__.py
taglogger/colors.py
taglogger/tlog.py
taglogger/version.py
tests/test_tlog.py
tests/test_version.py
taglogger-0.0.1.dist-info/LICENSE
taglogger-0.0.1.dist-info/METADATA
taglogger-0.0.1.dist-info/WHEEL
taglogger-0.0.1.dist-info/entry_points.txt
taglogger-0.0.1.dist-info/top_level.txt
taglogger-0.0.1.dist-info/RECORD
