Metadata-Version: 2.1
Name: taglogger
Version: 0.0.1
Summary: Simple logger that adds tags to log messages to make it easier to filter them
Home-page: https://github.com/joaompinto/taglogger
Author: João Pinto
Author-email: lamego.pinto@gmail.com
License: MIT
License-File: LICENSE
